seastate/__init__.py
seastate/exceptions.py
seastate/models.py
seastate/settings.py
seastate/utils.py
seastate/api/__init__.py
seastate/api/api_mediator.py
seastate/api/base.py
seastate/api/noaa_ndbc.py
seastate/api/noaa_tidesandcurrents.py
seastate/api/rest_adapter.py
seastate/data/__init__.py
seastate/data/noaa_ndbc.json
seastate/data/noaa_tidesandcurrents.json
seastate/data/parsers.py
seastate-0.2.1.dist-info/METADATA
seastate-0.2.1.dist-info/WHEEL
seastate-0.2.1.dist-info/licenses/LICENSE
seastate-0.2.1.dist-info/RECORD
