Metadata-Version: 2.3
Name: seastate
Version: 0.2.1
Summary: Collect ocean measurements for location and timeframe. Integrates NDBC and TidesAndCurrents datasources.
Project-URL: Homepage, https://github.com/ivorivetta/seastate
Project-URL: Issues, https://github.com/ivorivetta/seastate/issues
Author-email: Ivo Rivetta <ivo@ivorivetta.com>
License-File: LICENSE
Keywords: api,currents,data,forecast,marine,ndbc,noaa,ocean,temperature,tides,weather,wind
Classifier: License :: OSI Approved :: MIT License
Classifier: Operating System :: OS Independent
Classifier: Programming Language :: Python :: 3
Requires-Python: >=3.8.1
